<?xml version="1.0" encoding="utf-8"?>
<!DOCTYPE hibernate-mapping PUBLIC "-//Hibernate/Hibernate Mapping DTD 3.0//EN"
"http://hibernate.sourceforge.net/hibernate-mapping-3.0.dtd">
<!-- 
    Mapping file autogenerated by MyEclipse Persistence Tools
-->
<hibernate-mapping>
    <class name="com.ct.erp.lib.entity.VehicleEquip" table="tf_c_vehicle_equip">
        <id name="id" type="java.lang.Long">
            <column name="id" />
            <generator class="identity" />
        </id>
        <many-to-one name="vehicle" class="com.ct.erp.lib.entity.Vehicle" fetch="select">
            <column name="vehicle_id" />
        </many-to-one>
        <property name="channelId" type="java.lang.String">
            <column name="channel_id" length="30">
                <comment>收购渠道编号</comment>
            </column>
        </property>
        <property name="coverUrl" type="java.lang.String">
            <column name="cover_url" length="100">
                <comment>封面图片链接</comment>
            </column>
        </property>
        <property name="manufacturerName" type="java.lang.String">
            <column name="manufacturer_name" length="50">
                <comment>厂商名称</comment>
            </column>
        </property>
        <property name="doorCount" type="java.lang.String">
            <column name="door_count" length="30">
                <comment>车门数量</comment>
            </column>
        </property>
        <property name="mileageInFact" type="java.lang.String">
            <column name="mileage_in_fact" length="30">
                <comment>实际里程</comment>
            </column>
        </property>
        <property name="licenseInfo" type="java.lang.String">
            <column name="license_info" length="30">
                <comment>上牌信息</comment>
            </column>
        </property>
        <property name="starRating" type="java.lang.String">
            <column name="star_rating" length="30">
                <comment>车辆星级</comment>
            </column>
        </property>
        <property name="warrantyId" type="java.lang.String">
            <column name="warranty_id" length="30">
                <comment>质保等级编号</comment>
            </column>
        </property>
        <property name="warrantyFeeYuan" type="java.lang.String">
            <column name="warranty_fee_yuan" length="30">
                <comment>质保费用</comment>
            </column>
        </property>
        <property name="isFixedPrice" type="java.lang.String">
            <column name="is_fixed_price" length="30">
                <comment>是一口价</comment>
            </column>
        </property>
        <property name="allowedMortgage" type="java.lang.String">
            <column name="allowed_mortgage" length="30">
                <comment>是否可按揭</comment>
            </column>
        </property>
        <property name="mortgageNote" type="java.lang.String">
            <column name="mortgage_note" length="30">
                <comment>按揭说明</comment>
            </column>
        </property>
        <property name="sellingPoint" type="java.lang.String">
            <column name="selling_point" length="500">
                <comment>卖点描述</comment>
            </column>
        </property>
        <property name="maintainMileage" type="java.lang.String">
            <column name="maintain_mileage" length="30">
                <comment>保养里程</comment>
            </column>
        </property>
        <property name="hasMaintainHistory" type="java.lang.String">
            <column name="has_maintain_history" length="30">
                <comment>有无保养记录</comment>
            </column>
        </property>
        <property name="newCarWarranty" type="java.lang.String">
            <column name="new_car_warranty" length="30">
                <comment>manufacturer-厂商质保；seller-商家质保；none-无</comment>
            </column>
        </property>
        <property name="manufacturerConfiguration" type="java.lang.String">
            <column name="manufacturer_configuration" length="8000">
                <comment>车辆配置信息</comment>
            </column>
        </property>
        <property name="configurationNote" type="java.lang.String">
            <column name="configuration_note" length="2000">
                <comment>车型配置描述</comment>
            </column>
        </property>
    </class>
</hibernate-mapping>
